{
    "lang": "en", 
    "loc": [
        "PR"
    ], 
    "mdate": "2008-08-24", 
    "bookid": "1327", 
    "title": "Elizabeth and Her German Garden", 
    "author": "Von Arnim, Elizabeth, 1866-1941", 
    "subj": [
        "Gardening -- Fiction", 
        "Germany, Northern -- Description and travel", 
        "Gardens -- Fiction", 
        "British -- Germany -- Fiction", 
        "Germany -- Social life and customs -- 19th century -- Fiction", 
        "Women gardeners -- Fiction", 
        "Autobiographical fiction"
    ]
}